pycarla/__init__.py
pycarla/__main__.py
pycarla/carla.py
pycarla/synth.py
pycarla-0.1.2.dist-info/LICENSE
pycarla-0.1.2.dist-info/WHEEL
pycarla-0.1.2.dist-info/METADATA
pycarla-0.1.2.dist-info/RECORD
